NucleusApp/__init__.py
NucleusApp/app/__init__.py
NucleusApp/app/imports.py
NucleusApp/chest/__init__.py
NucleusApp/chest/container.py
NucleusApp/chest/exceptions.py
NucleusApp/config/__init__.py
NucleusApp/config/global_settings.py
NucleusApp/contrib/__init__.py
NucleusApp/modules/__init__.py
NucleusApp/modules/config.py
NucleusApp/modules/registry.py
NucleusApp-0.1b6.dist-info/DESCRIPTION.rst
NucleusApp-0.1b6.dist-info/METADATA
NucleusApp-0.1b6.dist-info/RECORD
NucleusApp-0.1b6.dist-info/WHEEL
NucleusApp-0.1b6.dist-info/metadata.json
NucleusApp-0.1b6.dist-info/top_level.txt
